polyglot/__init__.py
polyglot/__main__.py
polyglot/path.py
polyglot/arguments/__init__.py
polyglot/arguments/arguments.py
polyglot/arguments/position.py
polyglot/core/__init__.py
polyglot/core/beautify.py
polyglot/core/display.py
polyglot/core/extension.py
polyglot/core/ignore.py
polyglot/core/path.py
polyglot/core/polyglot.py
polyglot/core/project.py
polyglot/core/result.py
polyglot/core/tree.py
polyglot/exceptions/__init__.py
polyglot/exceptions/custom.py
polyglot/exceptions/exceptions.py
polyglot/ext/__init__.py
polyglot/ext/dir.py
polyglot/ext/env.py
polyglot/ext/extensions.py
polyglot/ext/json.py
python_polyglot-4.2.9.dist-info/LICENSE
python_polyglot-4.2.9.dist-info/METADATA
python_polyglot-4.2.9.dist-info/WHEEL
python_polyglot-4.2.9.dist-info/entry_points.txt
python_polyglot-4.2.9.dist-info/top_level.txt
python_polyglot-4.2.9.dist-info/RECORD
