Metadata-Version: 2.1
Name: python-polyglot
Version: 4.2.9
Summary: Find the percentage of programming languages used in your project
Home-page: https://github.com/pranavbaburaj/polyglot
Author: P Pranav Baburaj
Author-email: code-roller@googlegroups.com
License: UNKNOWN
Platform: UNKNOWN
Classifier: Programming Language :: Python :: 3
Classifier: License :: OSI Approved :: MIT License
Classifier: Operating System :: OS Independent
Requires-Python: >=3.6
Requires-Dist: requests
Requires-Dist: pyyaml
Requires-Dist: prettytable
Requires-Dist: clint
Requires-Dist: toml
